flask_logconfig/__init__.py
flask_logconfig/__meta__.py
Flask_LogConfig-0.4.2.dist-info/top_level.txt
Flask_LogConfig-0.4.2.dist-info/METADATA
Flask_LogConfig-0.4.2.dist-info/pbr.json
Flask_LogConfig-0.4.2.dist-info/DESCRIPTION.rst
Flask_LogConfig-0.4.2.dist-info/metadata.json
Flask_LogConfig-0.4.2.dist-info/WHEEL
Flask_LogConfig-0.4.2.dist-info/RECORD
